emb_model/__init__.py
emb_model/customized_dataset.py
emb_model/resources/classification_xgb_env.yaml
emb_model/resources/embedding_env.yaml
emb_model-0.2.43.dist-info/LICENSE
emb_model-0.2.43.dist-info/METADATA
emb_model-0.2.43.dist-info/WHEEL
emb_model-0.2.43.dist-info/top_level.txt
emb_model-0.2.43.dist-info/RECORD
