Metadata-Version: 2.1
Name: emb-model
Version: 0.2.43
Summary: simple useing for embedding models
Home-page: https://github.com/cheerzhang/EmbeddingModel
Author: ZhangLe
Author-email: zhangle@gmail.com
Project-URL: Bug Tracker, https://github.com/cheerzhang/EmbeddingModel/issues
Classifier: Programming Language :: Python :: 3
Classifier: License :: OSI Approved :: MIT License
Classifier: Operating System :: OS Independent
Requires-Python: >=3.9.0
License-File: LICENSE
Requires-Dist: torch==2.3.1
Requires-Dist: scikit-learn==1.5.1
Requires-Dist: numpy==1.26.4
Requires-Dist: pandas==2.1.4
Requires-Dist: xgboost==2.1.1
